<?xml version="1.0" encoding="UTF-8"?>
<java version="11.0.3" class="java.beans.XMLDecoder">
 <object class="java.util.ArrayList">
  <void method="add">
   <object class="Voiture">
    <void property="id">
     <int>1</int>
    </void>
    <void property="marque">
     <string>56</string>
    </void>
    <void property="modele">
     <string>468</string>
    </void>
    <void property="prixLocationParJour">
     <int>1</int>
    </void>
    <void property="vitesseMax">
     <int>61</int>
    </void>
   </object>
  </void>
 </object>
</java>
